{
  "lastUpdate": "2025-02-11 09:22:02 UTC",
  "activeTournament": 33,
  "questionsAsked": 3,
  "totalPlayers": 79,
  "ratings": {
    "Знаток": [
      {
        "username": "1173704494",
        "capital": 100,
        "points": 9.0,
        "remaining_boosters": 0,
        "wallet": 683.0,
        "tournament_questions": 3,
        "has_active_boosters": 0
      },
      {
        "username": "887446412",
        "capital": 100,
        "points": 9.0,
        "remaining_boosters": 0,
        "wallet": 874.0,
        "tournament_questions": 3,
        "has_active_boosters": 0
      },
      {
        "username": "7048289770",
        "capital": 100,
        "points": 9.0,
        "remaining_boosters": 0,
        "wallet": 1736.0,
        "tournament_questions": 3,
        "has_active_boosters": 0
      },
      {
        "username": "693187128",
        "capital": 100,
        "points": 9.0,
        "remaining_boosters": 0,
        "wallet": 945.0,
        "tournament_questions": 3,
        "has_active_boosters": 0
      },
      {
        "username": "1998199385",
        "capital": 100,
        "points": 6.0,
        "remaining_boosters": 0,
        "wallet": 446.0,
        "tournament_questions": 2,
        "has_active_boosters": 0
      },
      {
        "username": "510324011",
        "capital": 100,
        "points": 6.0,
        "remaining_boosters": 0,
        "wallet": 576.0,
        "tournament_questions": 2,
        "has_active_boosters": 0
      },
      {
        "username": "5310141893",
        "capital": 100,
        "points": 6.0,
        "remaining_boosters": 0,
        "wallet": 86.0,
        "tournament_questions": 2,
        "has_active_boosters": 0
      },
      {
        "username": "752735290",
        "capital": 100,
        "points": 6.0,
        "remaining_boosters": 0,
        "wallet": 433.0,
        "tournament_questions": 2,
        "has_active_boosters": 0
      },
      {
        "username": "859745879",
        "capital": 100,
        "points": 6.0,
        "remaining_boosters": 0,
        "wallet": 650.0,
        "tournament_questions": 2,
        "has_active_boosters": 0
      },
      {
        "username": "922045895",
        "capital": 100,
        "points": 6.0,
        "remaining_boosters": 0,
        "wallet": 127.0,
        "tournament_questions": 2,
        "has_active_boosters": 0
      },
      {
        "username": "1095733731",
        "capital": 100,
        "points": 6.0,
        "remaining_boosters": 0,
        "wallet": 233.0,
        "tournament_questions": 2,
        "has_active_boosters": 0
      },
      {
        "username": "5253427596",
        "capital": 100.0,
        "points": 3.0,
        "remaining_boosters": 0,
        "wallet": 601.0,
        "tournament_questions": 3,
        "has_active_boosters": 0
      },
      {
        "username": "103075256",
        "capital": 100,
        "points": 3.0,
        "remaining_boosters": 0,
        "wallet": 313.0,
        "tournament_questions": 1,
        "has_active_boosters": 0
      },
      {
        "username": "6118708118",
        "capital": 100,
        "points": 3.0,
        "remaining_boosters": 0,
        "wallet": 189.0,
        "tournament_questions": 3,
        "has_active_boosters": 0
      },
      {
        "username": "920084227",
        "capital": 100,
        "points": 3.0,
        "remaining_boosters": 0,
        "wallet": 84.0,
        "tournament_questions": 1,
        "has_active_boosters": 0
      },
      {
        "username": "673242969",
        "capital": 100,
        "points": 3.0,
        "remaining_boosters": 0,
        "wallet": 517.0,
        "tournament_questions": 1,
        "has_active_boosters": 0
      },
      {
        "username": "1354090059",
        "capital": 100,
        "points": 3.0,
        "remaining_boosters": 0,
        "wallet": 6.0,
        "tournament_questions": 1,
        "has_active_boosters": 0
      },
      {
        "username": "1451465410",
        "capital": 100,
        "points": 3.0,
        "remaining_boosters": 0,
        "wallet": 6.0,
        "tournament_questions": 1,
        "has_active_boosters": 0
      },
      {
        "username": "162553305",
        "capital": 100,
        "points": 3.0,
        "remaining_boosters": 0,
        "wallet": 593.0,
        "tournament_questions": 1,
        "has_active_boosters": 0
      },
      {
        "username": "1151940750",
        "capital": 100,
        "points": 3.0,
        "remaining_boosters": 0,
        "wallet": 318.0,
        "tournament_questions": 1,
        "has_active_boosters": 0
      },
      {
        "username": "5288388835",
        "capital": 100,
        "points": 3.0,
        "remaining_boosters": 0,
        "wallet": 459.0,
        "tournament_questions": 1,
        "has_active_boosters": 0
      },
      {
        "username": "64665575",
        "capital": 100,
        "points": 3.0,
        "remaining_boosters": 0,
        "wallet": 410.0,
        "tournament_questions": 1,
        "has_active_boosters": 0
      },
      {
        "username": "6775988014",
        "capital": 100,
        "points": 3.0,
        "remaining_boosters": 0,
        "wallet": 905.0,
        "tournament_questions": 1,
        "has_active_boosters": 0
      },
      {
        "username": "802254909",
        "capital": 100,
        "points": 3.0,
        "remaining_boosters": 0,
        "wallet": 148.0,
        "tournament_questions": 3,
        "has_active_boosters": 0
      },
      {
        "username": "1150465712",
        "capital": 100,
        "points": 3.0,
        "remaining_boosters": 0,
        "wallet": 72.0,
        "tournament_questions": 1,
        "has_active_boosters": 0
      },
      {
        "username": "531466669",
        "capital": 100,
        "points": 0.0,
        "remaining_boosters": 0,
        "wallet": 428.0,
        "tournament_questions": 2,
        "has_active_boosters": 0
      },
      {
        "username": "5382263197",
        "capital": 100,
        "points": 0.0,
        "remaining_boosters": 0,
        "wallet": 431.0,
        "tournament_questions": 2,
        "has_active_boosters": 0
      },
      {
        "username": "7765257894",
        "capital": 100,
        "points": 0.0,
        "remaining_boosters": 0,
        "wallet": 318.0,
        "tournament_questions": 2,
        "has_active_boosters": 0
      },
      {
        "username": "531226379",
        "capital": 100,
        "points": 0.0,
        "remaining_boosters": 0,
        "wallet": 537.0,
        "tournament_questions": 2,
        "has_active_boosters": 0
      },
      {
        "username": "631596086",
        "capital": 100,
        "points": 0.0,
        "remaining_boosters": 0,
        "wallet": 39.0,
        "tournament_questions": 2,
        "has_active_boosters": 0
      },
      {
        "username": "246054181",
        "capital": 100,
        "points": 0.0,
        "remaining_boosters": 0,
        "wallet": 0,
        "tournament_questions": 2,
        "has_active_boosters": 0
      },
      {
        "username": "656735138",
        "capital": 100.0,
        "points": -3.0,
        "remaining_boosters": 0,
        "wallet": 30.0,
        "tournament_questions": 1,
        "has_active_boosters": 0
      },
      {
        "username": "836555347",
        "capital": 100,
        "points": -3.0,
        "remaining_boosters": 0,
        "wallet": 324.0,
        "tournament_questions": 1,
        "has_active_boosters": 0
      },
      {
        "username": "268536143",
        "capital": 100,
        "points": -3.0,
        "remaining_boosters": 0,
        "wallet": 900.0,
        "tournament_questions": 1,
        "has_active_boosters": 0
      },
      {
        "username": "6543294995",
        "capital": 100,
        "points": -3.0,
        "remaining_boosters": 0,
        "wallet": 37.0,
        "tournament_questions": 1,
        "has_active_boosters": 0
      },
      {
        "username": "1309553080",
        "capital": 100,
        "points": -3.0,
        "remaining_boosters": 0,
        "wallet": 36.0,
        "tournament_questions": 1,
        "has_active_boosters": 0
      },
      {
        "username": "861992615",
        "capital": 100,
        "points": -3.0,
        "remaining_boosters": 0,
        "wallet": 1056.0,
        "tournament_questions": 1,
        "has_active_boosters": 0
      },
      {
        "username": "1326416100",
        "capital": 100,
        "points": -3.0,
        "remaining_boosters": 0,
        "wallet": 0,
        "tournament_questions": 1,
        "has_active_boosters": 0
      },
      {
        "username": "1362437339",
        "capital": 100,
        "points": -3.0,
        "remaining_boosters": 0,
        "wallet": 11.0,
        "tournament_questions": 1,
        "has_active_boosters": 0
      },
      {
        "username": "122766338",
        "capital": 100,
        "points": -3.0,
        "remaining_boosters": 0,
        "wallet": 11.0,
        "tournament_questions": 1,
        "has_active_boosters": 0
      },
      {
        "username": "1121326871",
        "capital": 100,
        "points": -6.0,
        "remaining_boosters": 0,
        "wallet": 26.0,
        "tournament_questions": 2,
        "has_active_boosters": 0
      }
    ],
    "Эксперт": [
      {
        "username": "471478283",
        "capital": 1599.0,
        "points": 287.82,
        "remaining_boosters": 28,
        "wallet": 2908.0,
        "tournament_questions": 3,
        "has_active_boosters": 1
      },
      {
        "username": "771127787",
        "capital": 1115.0,
        "points": 133.79999999999998,
        "remaining_boosters": 14,
        "wallet": 351.0,
        "tournament_questions": 2,
        "has_active_boosters": 1
      },
      {
        "username": "180975946",
        "capital": 1021.0,
        "points": 122.52,
        "remaining_boosters": 7,
        "wallet": 467.0,
        "tournament_questions": 2,
        "has_active_boosters": 1
      },
      {
        "username": "479033963",
        "capital": 1347.0,
        "points": 121.22999999999999,
        "remaining_boosters": 0,
        "wallet": 0.0,
        "tournament_questions": 3,
        "has_active_boosters": 0
      },
      {
        "username": "139124871",
        "capital": 1999.0,
        "points": 119.94,
        "remaining_boosters": 0,
        "wallet": 900.0,
        "tournament_questions": 2,
        "has_active_boosters": 0
      },
      {
        "username": "853175665",
        "capital": 1270.0,
        "points": 114.30000000000001,
        "remaining_boosters": 0,
        "wallet": 212.0,
        "tournament_questions": 3,
        "has_active_boosters": 0
      },
      {
        "username": "5188653846",
        "capital": 1827.0,
        "points": 109.61999999999999,
        "remaining_boosters": 0,
        "wallet": 510.0,
        "tournament_questions": 2,
        "has_active_boosters": 0
      },
      {
        "username": "722954860",
        "capital": 1146.0,
        "points": 103.13999999999999,
        "remaining_boosters": 0,
        "wallet": 150.0,
        "tournament_questions": 3,
        "has_active_boosters": 0
      },
      {
        "username": "636378515",
        "capital": 1100.0,
        "points": 99.0,
        "remaining_boosters": 0,
        "wallet": 56.0,
        "tournament_questions": 3,
        "has_active_boosters": 0
      },
      {
        "username": "478953639",
        "capital": 1562.0,
        "points": 93.72,
        "remaining_boosters": 0,
        "wallet": 357.0,
        "tournament_questions": 2,
        "has_active_boosters": 0
      },
      {
        "username": "SergeyKa",
        "capital": 1000.0,
        "points": 90.0,
        "remaining_boosters": 0,
        "wallet": 454.0,
        "tournament_questions": 3,
        "has_active_boosters": 0
      },
      {
        "username": "974777477",
        "capital": 1000.0,
        "points": 90.0,
        "remaining_boosters": 0,
        "wallet": 900.0,
        "tournament_questions": 3,
        "has_active_boosters": 0
      },
      {
        "username": "6466019730",
        "capital": 1000.0,
        "points": 90.0,
        "remaining_boosters": 0,
        "wallet": 662.0,
        "tournament_questions": 3,
        "has_active_boosters": 0
      },
      {
        "username": "442028467",
        "capital": 1190.0,
        "points": 71.39999999999999,
        "remaining_boosters": 0,
        "wallet": 102.0,
        "tournament_questions": 2,
        "has_active_boosters": 0
      },
      {
        "username": "1196575183",
        "capital": 1100.0,
        "points": 69.0,
        "remaining_boosters": 0,
        "wallet": 54.0,
        "tournament_questions": 3,
        "has_active_boosters": 0
      },
      {
        "username": "255049142",
        "capital": 1100.0,
        "points": 66.0,
        "remaining_boosters": 0,
        "wallet": 904.0,
        "tournament_questions": 2,
        "has_active_boosters": 0
      },
      {
        "username": "1345948649",
        "capital": 1100.0,
        "points": 66.0,
        "remaining_boosters": 0,
        "wallet": 967.0,
        "tournament_questions": 2,
        "has_active_boosters": 0
      },
      {
        "username": "977840664",
        "capital": 1100.0,
        "points": 66.0,
        "remaining_boosters": 0,
        "wallet": 915.0,
        "tournament_questions": 2,
        "has_active_boosters": 0
      },
      {
        "username": "SgtPepper",
        "capital": 1000.0,
        "points": 60.0,
        "remaining_boosters": 0,
        "wallet": 664.0,
        "tournament_questions": 2,
        "has_active_boosters": 0
      },
      {
        "username": "1772369433",
        "capital": 1286.0,
        "points": 38.58,
        "remaining_boosters": 0,
        "wallet": 0.0,
        "tournament_questions": 3,
        "has_active_boosters": 0
      },
      {
        "username": "6558249370",
        "capital": 1211.0,
        "points": 36.33,
        "remaining_boosters": 0,
        "wallet": 96.0,
        "tournament_questions": 3,
        "has_active_boosters": 0
      },
      {
        "username": "724066696",
        "capital": 1100.0,
        "points": 33.0,
        "remaining_boosters": 0,
        "wallet": 289.0,
        "tournament_questions": 1,
        "has_active_boosters": 0
      },
      {
        "username": "1031487037",
        "capital": 1000.0,
        "points": 30.0,
        "remaining_boosters": 0,
        "wallet": 872.0,
        "tournament_questions": 1,
        "has_active_boosters": 0
      },
      {
        "username": "957241577",
        "capital": 1295.0,
        "points": 0.0,
        "remaining_boosters": 0,
        "wallet": 112.0,
        "tournament_questions": 2,
        "has_active_boosters": 0
      },
      {
        "username": "1879077527",
        "capital": 1000.0,
        "points": 0.0,
        "remaining_boosters": 0,
        "wallet": 864.0,
        "tournament_questions": 2,
        "has_active_boosters": 0
      },
      {
        "username": "Адриано",
        "capital": 1000.0,
        "points": -30.0,
        "remaining_boosters": 0,
        "wallet": 405.0,
        "tournament_questions": 1,
        "has_active_boosters": 0
      }
    ],
    "Мастер": [
      {
        "username": "1877397832",
        "capital": 3999.0,
        "points": 719.8199999999999,
        "remaining_boosters": 18,
        "wallet": 125.0,
        "tournament_questions": 3,
        "has_active_boosters": 1
      },
      {
        "username": "Arhimed",
        "capital": 3900.0,
        "points": 351.0,
        "remaining_boosters": 0,
        "wallet": 3.0,
        "tournament_questions": 3,
        "has_active_boosters": 0
      },
      {
        "username": "1032851815",
        "capital": 2746.0,
        "points": 247.14,
        "remaining_boosters": 0,
        "wallet": 530.0,
        "tournament_questions": 3,
        "has_active_boosters": 0
      },
      {
        "username": "Тимур",
        "capital": 2149.0,
        "points": 193.41,
        "remaining_boosters": 0,
        "wallet": 839.0,
        "tournament_questions": 3,
        "has_active_boosters": 0
      },
      {
        "username": "1642969389",
        "capital": 2100.0,
        "points": 189.0,
        "remaining_boosters": 0,
        "wallet": 61.0,
        "tournament_questions": 3,
        "has_active_boosters": 0
      },
      {
        "username": "5176768913",
        "capital": 2015.0,
        "points": 181.35,
        "remaining_boosters": 0,
        "wallet": 457.0,
        "tournament_questions": 3,
        "has_active_boosters": 0
      },
      {
        "username": "Inna",
        "capital": 2039.0,
        "points": 122.33999999999999,
        "remaining_boosters": 0,
        "wallet": 1127.0,
        "tournament_questions": 2,
        "has_active_boosters": 0
      },
      {
        "username": "CAHEK",
        "capital": 2000.0,
        "points": 120.0,
        "remaining_boosters": 0,
        "wallet": 381.0,
        "tournament_questions": 2,
        "has_active_boosters": 0
      },
      {
        "username": "Melian",
        "capital": 2090.0,
        "points": -62.699999999999996,
        "remaining_boosters": 0,
        "wallet": 691.0,
        "tournament_questions": 1,
        "has_active_boosters": 0
      }
    ],
    "Босс": [
      {
        "username": "Als",
        "capital": 5090.0,
        "points": 152.7,
        "remaining_boosters": 0,
        "wallet": 1482.0,
        "tournament_questions": 1,
        "has_active_boosters": 0
      }
    ],
    "Титан": [
      {
        "username": "Archi",
        "capital": 7531.0,
        "points": 451.85999999999996,
        "remaining_boosters": 63,
        "wallet": 801.0,
        "tournament_questions": 1,
        "has_active_boosters": 1
      },
      {
        "username": "Константин",
        "capital": 7990.0,
        "points": 0.0,
        "remaining_boosters": 0,
        "wallet": 1600.0,
        "tournament_questions": 2,
        "has_active_boosters": 0
      }
    ],
    "Легенда": [],
    "Корифей": [],
    "Гуру": [],
    "IQ Капиталист": []
  },
  "totalPoints": {
    "Знаток": 87.0,
    "Эксперт": 2081.4,
    "Мастер": 2061.36,
    "Босс": 152.7,
    "Титан": 451.85999999999996,
    "Легенда": 0,
    "Корифей": 0,
    "Гуру": 0,
    "IQ Капиталист": 0
  },
  "prizePools": {
    "IQ Капиталист": 0.0,
    "Босс": 480.0,
    "Гуру": 400.0,
    "Знаток": 4000.0,
    "Корифей": 400.0,
    "Легенда": 400.0,
    "Мастер": 1040.0,
    "Титан": 480.0,
    "Эксперт": 2800.0
  },
  "playersByLevel": {
    "Знаток": 41,
    "Эксперт": 26,
    "Мастер": 9,
    "Босс": 1,
    "Титан": 2,
    "Легенда": 0,
    "Корифей": 0,
    "Гуру": 0,
    "IQ Капиталист": 0
  }
}